{"data": {"id": "430008248", "title": "Salzschifffahrt", "categories": ["Wanderweg"], "text": "So gelangen Sie in die Region Traunsee-Almtal (nach Stadl-Paura):<br><br><strong>Wir empfehlen Ihnen die Anreise mit den \u00f6ffentlichen Verkehrsmitteln!</strong><br><br><strong>per Bahn und Bus:</strong> bis zum Bahnhof Wels mit IC Z\u00fcgen auf der Westbahnstrecke&nbsp;(\u00d6BB und Westbahn) (Linie 101), dann umsteigen in die Regionalz\u00fcge in Richtung Attnang-Puchheim bis zum Bahnhof Lambach. Umsteigen auf die \"Vorchdorfer Bahn\" von Stern &amp; Hafferl (Linie 160) bis zum Bahnhof Stadl-Paura oder den O\u00d6VV Buslinie 504 Wels - Lambach nach Stadl-Paura, Haltestelle Traunbr\u00fccke, bei den Salzstadln, direkt am Themenweg<br><br><br>mit dem <strong>Traunstein Taxi Route 51 </strong>vom Bhf Lambach bis zum Schiffsleutmuseum, bitte mind. 1 Stunde vorab unter der <strong>Telefonnummer 050-422 1691</strong> bei der Taxi Zentrale anrufen oder auf der <a href=\"https://www.otaxi.at/\" target=\"_blank\" data-cke-saved-href=\"https://www.otaxi.at/\" rel=\"noreferrer\"><strong>otaxi App</strong></a> bestellen. Dieses Angebot ist nicht m\u00f6glich, wenn eine O\u00d6VV Busverbindung besteht!<br><br><strong>Bike &amp; Hike, Anreise mit dem Fahrrad:</strong><br>Von Wels bzw. Linz kommend auf dem <strong><a href=\"https://traunsee-almtal.salzkammergut.at/aktiv/radfahren-mountainbike-e-bike/radrouten/oesterreich-tour/detail/430001274/traunradweg-r4.html\" target=\"_blank\" data-cke-saved-href=\"https://traunsee-almtal.salzkammergut.at/aktiv/radfahren-mountainbike-e-bike/radrouten/oesterreich-tour/detail/430001274/traunradweg-r4.html\">R 4 Traunradweg</a></strong> bzw.<strong><a href=\"https://traunsee-almtal.salzkammergut.at/aktiv/radfahren-mountainbike-e-bike/radrouten/oesterreich-tour/detail/430002318/etappe-roemerradweg-voecklabruck-wels.html\" target=\"_blank\" data-cke-saved-href=\"https://traunsee-almtal.salzkammergut.at/aktiv/radfahren-mountainbike-e-bike/radrouten/oesterreich-tour/detail/430002318/etappe-roemerradweg-voecklabruck-wels.html\">R6 R\u00f6merradweg,</a> bzw. </strong>von Gmunden <strong><a href=\"https://traunsee-almtal.salzkammergut.at/aktiv/radfahren-mountainbike-e-bike/radrouten/oesterreich-tour/detail/430001274/traunradweg-r4.html\" target=\"_blank\" data-cke-saved-href=\"https://traunsee-almtal.salzkammergut.at/aktiv/radfahren-mountainbike-e-bike/radrouten/oesterreich-tour/detail/430001274/traunradweg-r4.html\">R 4 Traunradweg</a></strong> bzw von Passau \u00fcber V\u00f6cklabruck und Schwanenstadt auf dem <a href=\"https://traunsee-almtal.salzkammergut.at/aktiv/radfahren-mountainbike-e-bike/radrouten/oesterreich-tour/detail/430002318/etappe-roemerradweg-voecklabruck-wels.html\" target=\"_blank\" data-cke-saved-href=\"https://traunsee-almtal.salzkammergut.at/aktiv/radfahren-mountainbike-e-bike/radrouten/oesterreich-tour/detail/430002318/etappe-roemerradweg-voecklabruck-wels.html\"><strong>R 6 R\u00f6merradweg</strong></a> nach Lambach, <strong>beim Steg zur Dreifaltigskeitskirche die Traun queren und direkt am Themenweg bis zum Schiffleutmuseum fahren. </strong><br><br><strong>per Auto:</strong><br>Autobahn A1 Westautobahn Exit 207 Ausfahrt Vorchdorf beim Kreisverkehr - Richtung Lambach bis Stadl-Paura, ca. 10 Km<br>Bundesstra\u00dfe B1 bis Lambach - nach Stadl Paura, bei der Ampelkreuzung (Turm\u00f6ltankstelle) rechts in Richtung Ortszentrum, am Besten Parken bei der Dreifaltigkeitskirche und zu Fu\u00df zum Schiffleutmuseum.<br><br><strong>Parkm\u00f6glichkeiten:</strong> am Bahnhof Lambach, oder bei der Dreifalitigkeitskirche in Stadl-Paura und beim Schiffleutmuseum. <br><strong>Nutzen Sie bitte nur die daf\u00fcr vorgesehenen Parkpl\u00e4tze und nehmen Sie R\u00fccksicht auf privates Eigentum! Vielen Dank f\u00fcr Ihre Fairness!</strong><br><br><strong>Anreise mit \u00f6ffentlichen Verkehrsmitteln:</strong><br><br>", "city": "Stadl-Paura", "url": "https://www.oberoesterreich.at/oesterreich-tour/detail/430008248/salzschifffahrt.html", "geo": {"main": ["13.855197429656982", "48.078810086617231"], "geometry": "48.07884 13.85511 48.07987 13.85614 48.08005 13.85628 48.08043 13.85639 48.08061 13.85652 48.08109 13.8573 48.08134 13.85774 48.08172 13.85849 48.08192 13.85894 48.08191 13.85903 48.08207 13.86002 48.08217 13.86018 48.08228 13.86027 48.08231 13.86019 48.08242 13.86025 48.08256 13.86025 48.08322 13.86004 48.08342 13.85995 48.08359 13.85991 48.0837 13.85984 48.0842 13.85966 48.08454 13.85951 48.08482 13.85943 48.08495 13.85937 48.085 13.85937 48.0853 13.8595 48.08549 13.85951 48.08568 13.85944 48.08584 13.85942 48.08654 13.85944 48.08665 13.85946 48.08685 13.85966 48.08718 13.86005 48.08738 13.86016 48.08737 13.86044 48.08733 13.86072 48.08661 13.86313 48.08654 13.86346 48.08635 13.86488 48.08628 13.86524 48.08621 13.86538 48.0862 13.86549 48.08626 13.86566 48.0863 13.86606 48.08653 13.86674 48.08717 13.86836 48.08788 13.87023 48.08807 13.87079 48.08823 13.87136 48.08851 13.87221 48.0886 13.87255 48.08869 13.87288 48.08886 13.87312 48.08892 13.87327 48.08913 13.87402 48.08927 13.87466 48.08939 13.87529 48.08943 13.87551 48.08943 13.87569 48.08939 13.876 48.0894 13.87636 48.08939 13.87693 48.08935 13.87719 48.08928 13.87739 48.08921 13.87743 48.08912 13.87739 48.0888 13.87837 48.08856 13.87869 48.08843 13.87879 48.0877 13.87937 48.08742 13.87963 48.08656 13.88076 48.08631 13.88131 48.08604 13.88207 48.08599 13.88243 48.08598 13.88312 48.08606 13.88374 48.08621 13.8843 48.08644 13.88475 48.08713 13.8857 48.08777 13.88625 48.08794 13.88636 48.08822 13.88658 48.08858 13.88679 48.08864 13.88681"}, "ratings": []}}