{"data": {"id": "430000677", "title": "Vogellehrpfad-Runde R3", "categories": ["Themenstra\u00dfe", "Wanderweg"], "text": "PKW:<br>Von Linz in Richtung Bad Leonfelden/B126 fahren. Nach ca. 16 km in der Ortschaft Glasau an der Verkehrsampel rechts nach Hellmons\u00f6dt abbiegen.<br><br>POSTBUS:<br>Ab Linz (Hauptbahnhof, Hessenplatz, Urfahr, ...) mit Bus 260, 270 oder 300 nach Hellmons\u00f6dt/Marktplatz bzw. Glasau fahren.<br><br>", "city": "Hellmons\u00f6dt", "url": "https://www.oberoesterreich.at/oesterreich-tour/detail/430000677/vogellehrpfad-runde-r3.html", "geo": {"main": ["14.294437408098005", "48.431121718007681"], "geometry": "48.431122 14.294437 48.435108 14.290146 48.439094 14.289288 48.444169 14.283697 48.446162 14.286015 48.449009 14.286959 48.45105 14.292034 48.448432 14.291519 48.44809 14.295124 48.445243 14.295467 48.44308 14.298901 48.44081 14.298203 48.439322 14.298901 48.436019 14.299931 48.43283 14.301304 48.431236 14.294437 48.431236 14.294437"}, "ratings": []}}